smart_thinking_llm/__init__.py
smart_thinking_llm/datasets/__init__.py
smart_thinking_llm/datasets/base_dataset.py
smart_thinking_llm/datasets/data_classes.py
smart_thinking_llm/datasets/wikidata_dataset.py
smart_thinking_llm/find_patterns/__init__.py
smart_thinking_llm/find_patterns/base_pattern_finder.py
smart_thinking_llm/find_patterns/compositional_3_2_finder.py
smart_thinking_llm/find_patterns/pattern_runner.py
smart_thinking_llm/find_patterns/three_hop_finder.py
smart_thinking_llm/find_patterns/two_hop_finder.py
smart_thinking_llm/generation/__init__.py
smart_thinking_llm/generation/base_question_generator.py
smart_thinking_llm/generation/basic_question_generator.py
smart_thinking_llm/generation/bridge_21_generator.py
smart_thinking_llm/generation/bridge_31_generator.py
smart_thinking_llm/generation/compositional_question_generator.py
smart_thinking_llm/generation/price_computer.py
smart_thinking_llm/generation/question_runner.py
smart_thinking_llm/prices.json
smart_thinking_llm/prompts/basic_question_generation.txt
smart_thinking_llm/prompts/bridge_21_generation.txt
smart_thinking_llm/prompts/bridge_31_generation.txt
smart_thinking_llm/prompts/compositional_32_generation.txt
smart_thinking_llm/prompts/generate_triplets_prompt.txt
smart_thinking_llm/prompts/select_description_prompt.txt
smart_thinking_llm/tools/graph.py
smart_thinking_llm/tools/graph_creator/base.py
smart_thinking_llm/tools/graph_creator/graph_creator.py
smart_thinking_llm/tools/graph_creator/graph_creator_with_embeddings.py
smart_thinking_llm/tools/graph_creator/graph_creator_with_llm_selector.py
smart_thinking_llm/tools/path_converter.py
smart_thinking_llm/tools/split_file.py
smart_thinking_llm/utils.py
smart_thinking_llm-0.5.0.dist-info/METADATA
smart_thinking_llm-0.5.0.dist-info/WHEEL
smart_thinking_llm-0.5.0.dist-info/RECORD
