Metadata-Version: 2.3
Name: smart-thinking-llm
Version: 0.5.0
Summary: 
Author: VasilevGrigoriy
Author-email: vasiliev-greg@mail.ru
Requires-Python: >=3.11,<3.12
Classifier: Programming Language :: Python :: 3
Classifier: Programming Language :: Python :: 3.11
Requires-Dist: ipykernel (>=6.29.5,<7.0.0)
Requires-Dist: ipython (>=9.1.0,<10.0.0)
Requires-Dist: joblib (>=1.5.1,<2.0.0)
Requires-Dist: matplotlib (>=3.10.1,<4.0.0)
Requires-Dist: networkx (>=3.4.2,<4.0.0)
Requires-Dist: openai (>=1.72.0,<2.0.0)
Requires-Dist: pandas (>=2.2.3,<3.0.0)
Requires-Dist: python-dotenv (>=1.1.0,<2.0.0)
Requires-Dist: rapidfuzz (>=3.12.0,<4.0.0)
Requires-Dist: requests (>=2.32.4,<3.0.0)
Requires-Dist: scipy (>=1.16.0,<2.0.0)
Requires-Dist: seaborn (>=0.13.2,<0.14.0)
Requires-Dist: tiktoken (>=0.9.0,<0.10.0)
